sophuspy.cp36-win_amd64.pyd
sophuspy/sophuspy.cpp
sophuspy/include/extension/eigenex.hpp
sophuspy/include/extension/rootex.hpp
sophuspy/include/extension/se2ex.hpp
sophuspy/include/extension/se3ex.hpp
sophuspy/include/extension/so2ex.hpp
sophuspy/include/extension/so3ex.hpp
sophuspy/include/original/common.hpp
sophuspy/include/original/rotation_matrix.hpp
sophuspy/include/original/se2.hpp
sophuspy/include/original/se3.hpp
sophuspy/include/original/so2.hpp
sophuspy/include/original/so3.hpp
sophuspy/include/original/types.hpp
sophuspy/python/root.h
sophuspy/python/se2.h
sophuspy/python/se3.h
sophuspy/python/so2.h
sophuspy/python/so3.h
sophuspy-1.2.0.dist-info/LICENSE.txt
sophuspy-1.2.0.dist-info/METADATA
sophuspy-1.2.0.dist-info/WHEEL
sophuspy-1.2.0.dist-info/top_level.txt
sophuspy-1.2.0.dist-info/RECORD
