Metadata-Version: 2.1
Name: sophuspy
Version: 1.2.0
Summary: A python binding using pybind11 for Sophus, which is a C++ Lie library.(SO3 && SE3)
Home-page: https://github.com/craigstar/SophusPy
Author: Craigstar
Author-email: work.craigzhang@gmail.com
License: MIT
Keywords: Lie Group
Platform: all
Classifier: Programming Language :: Python :: 3
Classifier: Operating System :: OS Independent
License-File: LICENSE.txt
Requires-Dist: numpy
